{
    "id": "0-sc-connection-state",
    "name": "BACnetSCConnectionState",
    "base": "enumerated",
    "vendor": 0,
    "items": [
        {
            "name": "connected",
            "value": 1,
            "description": "The device is currently connected."
        },
        {
            "name": "disconnected-with-errors",
            "value": 2,
            "description": "The device is disconnected due to errors."
        },
        {
            "name": "failed-to-connect",
            "value": 3,
            "description": "The device failed to establish a connection."
        },
        {
            "name": "not-connected",
            "value": 0,
            "description": "The device is not currently connected."
        }
    ],
    "extensible": false,
    "minimum": 0,
    "maximum": 3,
    "ranges": [
        {
            "custom": false,
            "minimum": 0,
            "maximum": 3
        }
    ]
}
