{
    "alias": "BACnetStatusFlags",
    "name": "status-flags",
    "type": {
        "base": "bitstring",
        "bits": [
            {
                "position": 0,
                "name": "in-alarm",
                "description": "Object is in alarm."
            },
            {
                "position": 1,
                "name": "fault",
                "description": "Object is in fault condition."
            },
            {
                "position": 2,
                "name": "overridden",
                "description": "Object is overridden."
            },
            {
                "position": 3,
                "name": "out-of-service",
                "description": "Object is out of service."
            }
        ],
        "extensible": false,
        "range": {
            "minimum": 3,
            "maximum": 3
        },
        "ranges": [
            {
                "custom": false,
                "minimum": 3,
                "maximum": 3
            }
        ]
    }
}