{
    "$schema": "https://json-schema.org/draft/2020-12/schema",
    "$id": "https://baclib.github.io/if-struct.json",
    "title": "BAClib If-Struct Applicator",
    "type": "object",
    "if": {
        "properties": {
            "base": {
                "const": "struct"
            }
        }
    },
    "then": {
        "properties": {
            "fields": {
                "type": "array",
                "description": "Array of struct fields. Each entry must have a name and a type.",
                "minItems": 1,
                "items": {
                    "type": "object",
                    "properties": {
                        "alias": {
                            "type": "string",
                            "description": "An optional unique alias for the field."
                        },
                        "name": {
                            "type": "string",
                            "description": "The unique name of the field."
                        },
                        "context": {
                            "type": "integer",
                            "minimum": 0,
                            "description": "The context number of the field. Must be unique within the set."
                        },
                        "description": {
                            "type": "string",
                            "description": "An optional human-readable description for the field."
                        },
                        "type": {
                            "description": "The type of the field, either a type name or a reference to type traits.",
                            "oneOf": [
                                {
                                    "$ref": "./type-name.json"
                                },
                                {
                                    "$ref": "./type-traits.json"
                                }
                            ]
                        },
                        "optional": {
                            "type": "boolean",
                            "default": false,
                            "description": "Indicates if the field is optional. Defaults to false."
                        }
                    },
                    "required": [
                        "name",
                        "type"
                    ]
                }
            }
        },
        "required": [
            "fields"
        ]
    }
}